{
  "id": "lee8-261",
  "title": "1989年 新约福音祭司的尽职",
  "format": "html",
  "chapters": [
    {
      "number": 1,
      "title": "第一篇 新约福音祭司尽职的初步",
      "content": "读经：太三1~6，提前一16，彼前二9，罗十五16，十二1，西一28~29，彼前二5，路十1~6，约十五16。\n\n纲目\n\n壹 新旧约祭司职任的转变一 从施浸者约翰开始1施浸者约翰可算为旧约中末了一位祭司，但他弃而他转─太三1~42 他转为新约中神所命定的头一个福音祭司a 不是献牛羊等物为祭物b乃是献他传悔改的浸所得的罪人为祭物─太三5~6二有传福音的使徒们作榜样─提前一161广传福音，将所救来的人献与神为祭物─彼前二9，罗十五162带领所照顾的圣徒，将自己献与神作活祭─罗十二13用全般的智慧将圣徒在基督里成熟地献与神─西一28~29贰 信徒作新约福音祭司尽职的初步一该是普遍的祭司体系，不该是少数人的祭司职分─彼前二5二照神所命定的，访人传福音救罪人，献与神为祭物─路十1~6三如此亲自访人传福音，就是照主所派前去结果子─约十五16\n我们在这五次的特别聚会中，要专特的说到新约中一件奇特的事，就是神新约福音的祭司。说到祭司，我信许多人都知道这辞的意思；简单的说，祭司就是专心事奉神的人。照圣经的记载，关于祭司并不是一件小事。创世记一、二章给我们看见，神造人的时候，有几个特别的点。第一，神是照着祂的形像，按着祂的样式造人；这指明神要人彰显祂（一26上）。第二，神把地上掌管的权柄全都赐给祂所造的人，这表明神要人作祂的代表，在地上治理一切（一26下）。第三，神给人造了一个灵（二7），这灵乃是人接触、接受神的机关。第四，神把人造好之后，就把人摆在生命树跟前（二8，9），这指明神要祂按着自己的形像所造的人有祂的生命。所以，神造人的心意乃是要祂所造的人有神的形像彰显神，作神的代表替神在地上掌权。这一个神所造的人里面有灵，能以接触神，将神接受到他里面，作人的生命和一切生命的供应。神给祂所造的人有这样出于祂心意的安排，乃是要人事奉祂。事奉神就是作神的祭司。\n\n新旧约祭司职任的转变\n\n旧约圣经给我们看见，一个作祭司的人乃是一个事奉神、与神亲近的人。他是与神最亲密、最接近的人。神要祂的祭司把祂的话语，祂的心意，带着祂自己分赐给祂的百姓，并且把祂的百姓带到祂的面前，与祂联结。祭司一面把神带给人，一面也把人带给神。这就是旧约祭司的职任。\n\n从施浸者约翰开始\n\n我们知道，旧约所说的事多半都是预表，都是影儿。这些预表、影儿，到了新约就都应验、成全了。关于祭司这件事也不例外，到了新约，祭司的预表应验了，祭司的影儿成全了。关于祭司的职任，从旧约到新约有一个大的转变。这个转变开始于施浸者约翰的身上。施浸者约翰生于祭司的家庭，他是领班的祭司撒迦利亚的独生儿子。所以按着神的定规，他生来就是祭司。照圣经的记载来看，施浸者约翰可算为旧约中末了一位祭司，但他弃而他转。当他长大成人，要尽祭司的职任时，他本该住在圣殿里学习作祭司，也应该吃祭司的食物，穿祭司的衣服，作祭司的工作。但是，他却住在旷野里，那是一个野地，没有文化、宗教的事（太三1~4）。他所过的生活也是一种野的光景，穿的是骆驼毛，吃的是蝗虫野蜜。他作的事看起来也很粗野，他大声传悔改归神的道，并且把悔改的人一个个浸到水里去。从此，在他身上就有了新旧约祭司职任的转变，从物质的转到属灵的，这是非常奇特的。\n\n献悔改的罪人为祭物\n\n在旧约，祭司主要的是献牛羊等牲畜为祭物。但这里施浸者约翰所献的乃是悔改的罪人。他转为新约中神所命定的头一个福音祭司，不是献牛羊等物，乃是献他传悔改的浸所得的罪人为祭物（太三5~6）。所以，从施浸者约翰开始，新约福音祭司主要所作的就是把救来的罪人，当作祭物献给神。新约福音的祭司不像旧约那样，在牛羊身上作工，乃是在罪人身上作工。\n\n有传福音的使徒们作榜样\n\n\n传全备的福音\n\n新约福音的祭司在罪人身上的工作是完满的，其中有三大部分。第一部分，带领罪人悔改、信主，罪得赦免，灵里得着重生。这也是神救恩的第一步。第二部分，带领悔改、重生的人魂里逐渐变化。罗十二2说，“要借着心思的更新而变化。”心思是我们人魂里的主要部分，心思的更新就是魂的变化。我们一时之间灵里得了重生，之后还需要长期的变化。这变化的过程，就是一再的让基督在我们里面每一部分扩展，扩展到我们的心思、情感、意志里。当主这样在我们里面一部一部扩展、变化我们时，我们也就在祂里面长大。第三部分，当我们在主里长大以至成熟，至终主来的时候，我们的身体要改变形状，完全得赎（腓三21）。这样，我们全人，灵、魂、体，被主充满、浸透，从里到外与主调和为一。祂成为我们，我们成为祂；祂在我们里面作我们的生命，我们在外面作祂的彰显。这就是神救恩的全部，也是使徒们所传讲全备的福音。所以，神新约的福音不仅使我们的灵得重生，并且使我们的魂得变化，最终使我们的身体得赎，好叫我们全人，灵、魂、体都蒙拯救。神新约福音的祭司就是在人身上作这三步的工作。\n\n作神福音的祭司\n\n使徒保罗所写的罗马书是论到神的福音，从罪人说起；说到一个罪人如何信主得救、称义，在基督里长进、圣别、变化，将自己献与神作活祭，好成为基督身体上的肢体，过召会的生活，共同彰显基督，并等候主来。保罗不仅这样说神的福音，他也作这样的福音祭司。他受神差遣，一地一地广传福音，将所救来的人当作祭物献与神（罗十五16，彼前二9）。然后，继续在得救的人身上作喂养、顾惜的工作，好带领他们，将自己献与神作活祭（罗十二1）。保罗就是这样一个福音祭司的榜样。他照顾在基督里的初信者，使他们因神的话语得着增长，借此福音的果子得以常存。他且进一步在他们身上作教导、成全的工作，他是天天在圣徒身上单独、直接的工作，使他们的恩赐都被成全，同样会作建造基督身体的工作（弗四12），个个也成为新约福音的祭司。\n\n使徒能，信徒也能\n\n照着圣经的启示，每一个在基督里的信徒都是福音的祭司，都该像使徒保罗那样出去对人传福音，把人救来，浸入三一神里面，当作祭物献与神。这是新约福音祭司工作的开始，接着我们还得喂养得救的人。传福音带人信主，这是属灵的生（林前四15），就是用主的话和生命重生他们。借着受浸，他们成了在基督里初生的婴孩。这时候我们就得好好喂养、顾惜他们，使他们在生命里长大。进一步，我们还得教导他们，一面像乳养的母亲，顾惜自己的孩子（帖前二7）；一面像劝导的父亲，照顾他们（帖前二11），如同使徒保罗一样。\n使徒保罗住在以弗所有三年之久，他挨家挨户地教导那里的圣徒，昼夜不住地流泪劝戒他们各人。凡关乎神旨意的，他没有一样避讳不告诉他们（徒二十31，20，27）。今天我们也该这样效法保罗的榜样，教导、成全弟兄姊妹。他所作的，我们也能作，并且当我们会作了，也该教导、成全别人，使他们也能作。这样，每一个圣徒都能成为尽职的福音祭司，都能在罪人身上作神完全救恩的工作：传扬福音，使人重生；喂养初信者，使他长大；教导圣徒，使他被成全；培养人申言，为神说话，好达到建造基督的身体。\n\n信徒作新约福音祭司尽职的初步\n\n我们得救的信徒都是福音的祭司，保罗是福音的祭司，你我也都是福音的祭司。谁也不能代替谁作祭司。保罗传福音结果子，你我也该传福音结果子。我们既是福音的祭司，就该在罪人身上作工。也许有人会说，我不会作，我作不好。你不会作，你作不好，那是因为你不作、不多作、不常作。你我若是肯作、多作、常作，一定会作，并且越作越好。\n\n普遍的祭司体系\n\n我们既是福音的祭司，就要向神献祭，将所救来的罪人献与神。照圣经的启示，这样的尽职该是普遍的祭司体系，不该是少数人的祭司职分（彼前二5）。所有的信徒构成一个祭司的国度，他们就是一个祭司的体系。不是少数得救的人，有特别的恩赐，他们是祭司，其他大多数的人没有什么恩赐，就不能作祭司。这是不合乎圣经的。圣经是说，我们每一个信徒都是神福音的祭司。照着我们天然的人来说，我们不会传福音。但是，在我们得救、重生的时候，我们得着了一个新生命，就是神的生命。这生命有其生机的功能，这功能需要得着启发并发展。\n虽然如此，今天基督教的光景并不是这样，所有聚会和事奉的作法并不能叫圣徒属灵生机的功能得着启发，只不过叫少数有恩赐、专门的人有分于圣工。这些人就作了神职人员，形成了圣品阶级，一切关乎事奉神的事都由他们来作，其他的人都是平信徒，最多只是在事务上帮忙而已。\n\n访人传福音，前去结果子\n\n今天在主的恢复里，主在我们身上所要恢复的，就是普遍的祭司职任，而且是普遍的福音祭司。在我们中间，每一个得救的人都是祭司，都是“神职人员”，都该自己直接的传福音，对家人、对亲戚、对同事、对同学、对邻舍传福音。这样的传福音就是为主所派前去结果子（路十1~6，约十五16）。我们都是主这葡萄树上的枝子（约十五5），需要亲自结果子，不能叫别人代替。我们应该亲自访人传福音，带领人得救、重生，并且喂养、教导、成全人。\n如果这里汉城的召会有三千位圣徒，只靠少数的同工和长老召聚大会传福音，其他二千九百多人不过是帮忙的。这样一年下来，带进来的人一定非常有限。但是，今晚在座三千位的弟兄姊妹听了这一篇信息，看见自己是福音的祭司，若都肯去在罪人身上作工，一年之后，我绝对相信每一个人都能有一个常存的果子，不仅献与神为祭物，也能带进召会中。我们有三千位的圣徒，就有三千个福音祭司，个个都在罪人身上作工，拯救人、喂养人，教导人并成全人，使他们也能作我们所作的。结果，召会年年就会有一倍的繁增，圣徒也都有长进，有事奉，尽福音祭司的职分，建造基督的身体。\n李常受弟兄于主后一九八九年四月二十七日讲于韩国汉城\n\n第一篇"
    },
    {
      "number": 2,
      "title": "第二篇 喂养照顾初信者",
      "content": "读经：约二一15，十五16，帖前二7，罗九5，提前二5，路二11，林前十五45下，约四24，罗十12，彼前二2，罗十二1，徒五42。\n\n纲目\n\n壹喂养主的小羊─约二一15一使我们所结的果子常存─约十五16二如乳母顾惜自己的孩子─帖前二7三 带领初信者：1 认识主a是神─罗九5b是人─提前二5c是救主（包括救赎主）─路二11d是赐生命的灵─林前十五45下2认识他们有重生的灵，可以敬拜神（主）─约四243呼求主名，祷告主，吸取主的丰富─罗十12四带领他们在生命上长大，能将自己献与神作活祭─彼前二2，罗十二1贰 为着喂养初信者，须到他们家中聚会：一这是新约所启示的榜样─徒五42二 也是新约信徒作福音祭司尽职所需要的第二步\n在上一篇信息，我们看见神在新约中是叫每一个得救的人都作福音的祭司；不光是作祭司，乃是作福音的祭司。作神福音的祭司就是用神的福音在罪人身上作工。这样的工作主要的有三个步骤。第一步，用神的福音把罪人救来献与神为祭物。第二步，用神的恩典供应这些得救的人，使他们长大，把自己献与神作活祭。第三步，用神的智慧把这些圣徒一个一个的在基督里成熟地献与神。这是新约所给我们清楚看见神福音祭司尽职的三步；这也就是神福音全盘的工作。这样一个全盘的工作不是少数人才作的，乃是你我每一个得救的人都要作的，因为我们都是新约福音的祭司。在召会中并没有两等人，圣品阶级和平信徒；只有一班人，个个都是圣徒，也都是福音的祭司，都该尽福音祭司的职分。我希望我们能把这件事听得清楚，也看得准确。\n\n生了还要养\n\n从旧约我们看见，一个作神祭司的人乃是一个有神的形像彰显神，有神的权柄代表神，有神的生命活出神的人。他也是一个和神交通、亲近神、与神联结的人。他还是一个申言者，为神说话。他既是这样一个人，就能把神带来给人，也能把人带去给神。到了新约，这样一个祭司乃是一个得救、重生、经历基督完全救恩、享受基督一切丰富的人。他不仅能把神的救恩带给人，更能把神的基督这活的人位分给人，因而把罪人救来献与神为祭物，并带领他在生命里长大、变化，将自己献与神作活祭，且用全般的智慧教导、成全他，至终把他在基督里成熟地献给神。这是我们每一个人都应当作的。无论是年长的、年幼的，得救多年的，或是初得救的，都应该在罪人身上作这样的福音工作。\n我们这些在基督里的信徒都应该生养属灵的孩子。我们借着福音，使罪人得重生，成为神的儿女，然后在主里喂养他，使他长大。按肉身说，生一个孩子大概需要一年。这件事用在属灵方面可说是最合式的，一年生一个。然而，我们基督徒在传福音生属灵孩子的事上，常常是不平衡的。冷淡的时候，就一点都不传福音，甚至八年、十年都不生一个；等到复兴了，大发热心，就巴不得生一大堆。这两种情形都不对，不生固然不好，生了一大堆却不能养也不好。所以，我们必须按照生命的定律，一年好好的生一个。我们的难处要不是不生，就是多生不养。难怪在召会中初得救的好多，但是带进来的却寥寥无几。\n\n喂养主的小羊\n\n所以，我们要传福音拯救人，使人得重生，更要喂养初得救的人。约翰二十一章，主复活后，向彼得显现，对他说，“你爱我比这些更深么？”彼得说，“主啊，是的，你知道我爱你。”主对他说，“你喂养我的小羊。”（15）喂养小羊就是用里面生命的丰富滋养幼弱的信徒。这需要我们爱主，享受祂神圣生命的丰富。当我们享受主作我们丰盛的生命供应，我们就该并且就能喂养主的小羊。\n\n作神福音祭司的资格\n\n喂养主的小羊也是神福音祭司的工作。作为一个神福音的祭司，需要有十项资格。第一，有神的形像，能彰显神。第二，有神的权柄，能代表神。第三，有神的生命，能活出神。第四，是与神交通，亲近神的人。第五，是与神成为一灵、联合为一的人。第六，作神的申言者，为神说话。第七，能把神带给人，并把人带给神。第八，经历基督完全的救恩，享受基督一切的丰富。第九，能把基督分赐给人。第十，能把所喂养、照顾的人在基督里成熟地献给神。我们必须是这样的人，才能去喂养主的小羊，照顾初信的人。\n\n如同乳母顾惜自己的孩子\n\n喂养主的小羊等于乳母用自己的奶滋养主里的孩子。每一个喂养别人的人都是主里的乳母，用自己的奶，就是用自己的所是、所有并所能来供应人。为此，我们必须是一个正当且丰富的人。否则，我们即使带人得救、重生了，我们若不是一个在生活中彰显神，代表神，活出神，与神交通，享受神，把神带给人的人，我们还是不能喂养初信的人。看望人的时候，只是自己去，而不是带着神去，也就说不出亮光和生命的话来供应属灵的孩子，最多不过是有一点问候和交通罢了，不能真正供应人生命，满足人的需要。这样的看望是空洞的、无效的。\n你我必须是一个彰显神，代表神，活出神，与神交通，亲近神，与神成为一的人。这样，当你去照顾新蒙恩的人时，他一看见你，自然就会受感动。你的面容，你的气味就彰显神，你的谈吐，你的举止就代表神，你把神带到他那里去了，并且把神分赐给他。卖珠宝的人不是到处宣传，空说珠宝的价值，他乃是带着珠宝而来，让人一看便知。我们作神福音祭司的，就是这样一个带着珠宝的人。基督就是我们的珠宝，神就是我们的珠宝；我们不光是出去讲基督，述说神，更是彰显神、代表神、活出神，把神带给人。我们天天经历基督的救恩，时时享受基督的丰富，里外都满了基督，人一看到我们，就看到了基督；一碰着我们，就碰着了基督。这是正确的传福音，也是真正的喂养人，使人里面活过来，且得着饱足。\n\n带领初信者认识主、用灵接触主并长大\n\n我们喂养照顾初信的人，首先要带领他们认识主是谁。祂乃是在万有之上，永远受颂赞的神（罗九5）。我们的主耶稣乃是独一的真神，除祂以外，再没有别神。不仅如此，这位主祂还是人（提前二5）。祂是神成为人，是奇妙的神而人者，兼有神人二性。祂是完整的神，也是完全的人。这位是神又是人的主耶稣乃是我们的救主和救赎主（路二11）。祂钉十字架并且复活，救赎了我们，也拯救了我们。祂在复活里且成了赐生命的灵（林前十五45下），住在我们这些信祂者的里面。\n我们这样带领初信者认识主是神，是人，是救主，是赐生命的灵之后，就要帮助他们认识自己有重生的灵。当我们信主而重生时，神的灵就进到我们里面，将我们的灵点活，并且住在我们的灵里，使我们可以在灵里敬拜神（约四24）。神的灵，就是主耶稣，既然活在我们里面，我们就能借着呼求主名，祷告主，吸取主的丰富。祂对一切呼求祂的人是丰富的（罗十12）。这时候，我们就要带初信的人呼求主，喊“哦，主耶稣！”不光用口称呼，且要从深处的灵里呼求。这样的呼求就像作深呼吸一样，使我们从主得着生命的供应。我们也可以带领他向主祷告：“哦，主耶稣，我需要你。哦，主耶稣，你是我的救主，我向你敞开。哦，主耶稣，求你进到我里面，作我生命的供应。”当我们这样带领初信者对主有基本的认识，并且会用灵接触主，吸取主的丰富，他就能时常得着主的供应，在生命里长大（彼前二2），到一个地步，就能将自己献与神作活祭（罗十二1）。\n\n到初信者家中聚会\n\n为着喂养初信者，带领他们在生命里长大，成为常存的果子，我们需要到他们家中聚会，与他们同聚，亲自带领、喂养他们。这样，久而久之他们就能被成全，和我们一样。我们是什么样的情形，我们所喂养照顾的人也就是什么情形。我们若是一个爱主的人，常和主交通，与主非常亲密，甚至与主联合为一，当我们一次一次的去喂养照顾初信的人，结果他们一个个就会变得和我们一样，不爱世界，单单爱主，时常被主充满，到一个地步，他们就能把自己献与神作祭物。起先是我们借着福音将他们救来，当作祭物献给神；现在，他们经过喂养照顾，在生命里长大了，也把自己当作活祭献给神。这样到初信者家中聚会，喂养照顾他们，乃是新约所启示的榜样（徒五42），也是我们作神福音祭司尽职所需要的第二步。这是我们每一个弟兄姊妹都能也都应该作的。这是何等荣耀的事。\n李常受弟兄于主后一九八九年四月二十八日讲于韩国汉城\n\n第二篇"
    },
    {
      "number": 3,
      "title": "第三篇 教导成全圣徒",
      "content": "读经：来十24~25，帖前二11，徒二十20，27，31，西一28~29，弗四11~12。\n\n纲目\n\n壹与圣徒聚富于彼此互相性的小排聚会─来十24~25一 带领启发圣徒：1 互相敞开，彼此交通2 互相代祷3 彼此照顾、牧养4 彼此发问，学习并教导真理5 彼此发问，追求并指导生命的长大二劝勉、抚慰圣徒像父亲─帖前二111将神一切的旨意教导圣徒─徒二十20，27，312用全般的智慧，将圣徒成熟地献与神─西一28~293装备、供应圣徒，使他们能作新约职事的工作，就是建造基督生机的身体─弗四11~12三 指派圣徒前去：1 访人传福音2 喂养照顾初信者3 带领信徒参加小排聚会4 带领信徒参加召会较大的聚会贰 这是召会实行生活的主要部分叁 也是新约圣徒作福音祭司尽职的第三步\n本篇信息我们要来看新约福音祭司第三步的工作，教导成全圣徒。我们不仅喂养照顾初信者，我们还要教导成全他们。一个小孩子生下来，要养也要教。若是生了不养，就夭亡了；若是生了，也养了，却不教，还不能得成全。所以，一个小孩子长到某种程度，就需要教。按着人肉身的生命说，我们需要生、养、教，就属灵的生命说，也是这样。我们作新约福音的祭司，在罪人身上作工，借着福音将他们救来归神，还要去到他们家中聚会，喂养照顾他们，且要带他们来聚富于彼此互相性的小排聚会。\n\n小排是我们自己的聚会\n\n希伯来十章二十四、二十五节说，“当彼此相顾，激发爱心，勉励行善；不可放弃我们自己的聚集，…倒要彼此劝勉。”这里的聚集就是我们所说的小排聚会，满了彼此互相的性质。这绝不是一个一人讲众人听的大聚会，乃是一、二十人的聚集，彼此交通，互相教导。实在说来，在我们基督徒的召会生活中，小排聚会乃是主体。可惜的是，召会在地上经过一千九百多年，逐渐把这样的聚会轻忽而丢失了，以致今天的基督教大体说来并不强壮。成千上万的信徒由于失去了照顾和教导，也就落到荒凉的光景中。我们若要彼此相顾、教导、勉励，就需要有小排聚会。\n小排聚会乃是我们基督徒自己的聚会。一个基督徒若不去小排聚会，就是放弃自己的聚会。认真的说，像今晚这么大的聚会并不是你们大家的聚会，乃是我的聚会。你们是在赴我的聚会，听我讲道。等到你们有了小排聚会，十几二十个人来在一起，没有人讲道给你们听，也没有人去带领你们，样样都由你们自己来。那就道道地地是你们自己的聚会。也许你们要问，在这种小排的聚会里，你们要作什么。我先对大家这样说，小排聚会不是作礼拜，也没有规条或程序，我们这些圣徒就是预定一个日期、时间，到时候大家来在一起，聚我们自己的聚会。\n我常常愿意说，我们基督徒乃是一班聚会的人。我们还没有来在一起时，在家里就唱诗歌了，就祷告了。我们天天祷告，时时赞美主。在生活中，我们就唱、就祷。也不一定是有小排聚会的那一天才这样，就是别的日子，我们也唱、也祷。我们的生活就是唱诗祷告的生活。我们是个又唱诗又祷告的基督徒。每天早晨一起来，就呼喊主名，然后又唱又祷，自然就得胜了。若是我们哑口无声，没有唱也没有祷，我们就是失败的。但什么时候我们一开口呼求，一唱诗祷告，鬼魔就都逃跑，我们也就复兴、得胜了。当我们过这样的生活，天天祷告唱诗，小排聚会还没有到，我们已经从家里开始了。所以我们来在一起，自然就有话说，或祷告，或唱诗，都会满有主的同在。\n\n聚富于彼此互相性的小排聚会\n\n小排聚会首先重在带领启发圣徒，使他们能互相敞开，彼此交通；有什么需要或难处，都可以真实地说出来，在交通中互相代祷；进而彼此照顾、牧养，无论是属灵或生活上的，都能彼此担就、供应。所以，每一次的小排聚会就是这样的生机，没有既定的程序或节目，全凭与会的人随从灵，照着现实的情况而有所交通。还有，在这样的聚会中，关于圣经的问题都可以提出来，彼此发问，好学习并教导真理。一个刚信主的姊妹或许就问说什么叫作重生，其余的人听到以后，都可以照着自己所知道的来答复。有人说，“重生就是在我们人的天然生命之外，又得着神的生命。”他这么一说，人就受了教导，原来重生并不像不信的人所说的，已往的一切譬如昨日死，今后的一切譬如今日生。这时候，有人还可以加上一点：“不错，重生使我们得着神的生命，而这生命和圣灵是不能分的。我们要跟随灵而行，就能凭着神的生命活着了。”就这样，每一个人，无论是年长、年幼，或弟兄、姊妹，都照着自己的经历和领会说，只需要几分钟的时间，弟兄姊妹对于这个问题就受了美好的教导。\n我们这样的小排聚会，并不需要一个所谓的传道人，专门讲道给人听，解答各种问题，像是带领一个查经聚会。我们聚小排聚会乃是彼此互相的，我也发问，你也发问；我也讲，你也讲。我加一点，你加一点，他也加一点，结果聚会就活了，也丰富了。所有与会的人都看见了，也听见了，也就学了真理。这比一个讲道先生每次从头到尾讲一个题目，好太多了。但这样的聚会，说难不难，说容易也不容易，完全在乎我们的操练。我们要学习在小排聚会中互相敞开，彼此交通，互相代祷，彼此照顾、喂养，还能彼此发问，无论是真理或生命的问题，我们都能一同学习并教导，一同追求并指导生命的长大。\n这样看来，我们的小排聚会是有多方面的功能的。为此，第一，我们在家里平常就要有唱，有祷。第二，来在一起就彼此敞开、交通，有代祷、照顾、喂养。第三，还能彼此发问，一同解答。凡是关乎真理或生命的问题，都能提出来，各人照着自己所知道的来回答；知道得多就答得多，知道得深就答得深，加在一起，就是召会的丰富。我们大家都这样来操练，越操练就越会，越会就越丰富。如此一来，每一个在小排里的人就都得了成全。\n\n小排聚会重在教导成全\n\n弗四11告诉我们，神赐给召会一些有特别恩赐的人，有使徒、申言者、传福音者、牧人和教师，好为着成全圣徒。这些人不是把主所赐给他们的恩赐拿去自己运用，以发展主的事工。他们乃是要成全众圣徒。申言者成全圣徒申言，使个个都能为神说话；传福音者成全圣徒传福音，使个个都会作福音的祭司拯救罪人；牧人和教师成全圣徒，使个个都能喂养、教导；甚至有使徒成全圣徒，使他们能作使徒。一个人得救以后，就算得到喂养、照顾也还不够 ；如何传福音，为主申言，喂养别人，他还是不会。所以他需要得着恩赐的成全。当每一个圣徒得了成全，他就能作职事的工作，就是建造基督的身体（弗四12）。不是有恩赐的人直接建造，乃是这些人成全众圣徒，由他们来建造。\n为这缘故，在小排聚会中，我们要劝勉、抚慰圣徒，像父亲待自己的孩子（帖前二11），在适当的机会，将神一切的旨意全都教导他们（徒二十20，27，31），如同使徒保罗所作的，用全般的智慧，劝戒、教导各人，直到把各人在基督里成熟地献与神（西一28~29）。到这时候，这些被成全的圣徒就能作有恩赐的人所作的，就能受指派前去访人传福音，喂养、照顾初信者，并带领信徒参加小排聚会，还要带领信徒参加召会较大的聚会，使他们能照顾、教导别人，也能为主申言，供应基督。这是召会生活实行的主要部分，也是新约圣徒作福音祭司尽职的第三步。这样的事是我们每一个人都能作的，也都该作的。愿主祝福我们。\n李常受弟兄于主后一九八九年四月二十九日讲于韩国汉城\n\n第三篇"
    },
    {
      "number": 4,
      "title": "第四篇 申言建造召会",
      "content": "读经：林前十四3~5，12，1，31，24，26。\n\n纲目\n\n壹 是新约福音祭司尽职的完成一申言为主说话建造召会─林前十四3~5二这是新约诸般恩赐中之超越者─林前十四12三是切慕属灵恩赐的信徒尤其该切慕的─林前十四1四是信徒人人都能作，也是信徒人人都该作的─林前十四31，24贰 是新约福音祭司尽职的目标一 福音的祭司传福音救罪人献给神，是为着此一目标二 喂养初信者，带领他们在生命上长大，将自己献给神作活祭，也是为着此一目标三 成全圣徒，用全般的智慧教导圣徒，将他们在基督里成熟地献与神，也是为着此一目标四 圣徒被成全得以长大成熟，在真理上有深造，在生命上有经历，就能申言，将基督供应祂的众肢体，使召会得着生机的建造五 新约信徒作神福音的祭司，都当竭力追求，达到此一目标，以完成神新约的经纶叁需要有召会性彼此说互相听的聚会─林前十四26一 与会者人人都当有可供应聚会的二 一切都当为着建造圣徒与召会三 满了基督丰富的供应与展览\n在前面几篇的信息中，我们看了新约福音祭司的头三步重要工作；这三步重要的工作，是每一个新约的信徒都该作，也都能作的。新约的信徒都是神福音的祭司，个个都要去传福音救罪人，把他们当作祭物献给神；并且继续喂养、照顾初信的人，还要教导、成全他们，直到他们都能作那些有恩赐的人所作为着建造基督身体的工作。\n\n作福音祭司的工作需要训练与操练\n\n新约福音祭司这三步重大的工作，照新约的启示，并不是按着人天然的作法。就人的天然说，个个信徒似乎都可以传福音救罪人，都可以喂养照顾初信者，并且可以教导、成全圣徒。但就属灵的机能说，并非如此。这福音祭司的工作不是去作就可以了，它需要有训练。为此，我深深盼望这里的召会从现在起能训练圣徒们，个个都会传福音。传福音的讲究很大，也很多。首先，需要认识主耶稣是谁，并祂的救恩是什么；祂是神如何经过了种种的过程，成功救赎，成了赐生命的灵，来作我们的拯救。我们还要知道人的三部分─灵、魂、体；人怎样堕落变成肉体，而肉体又如何属于天然的魂生命，是败坏到极点的，但人里面却有一部分为神保留，就是灵。\n我稍微说一点，你们就了解了，去传福音需要受训练，不只在真理上、认识上需要受训练，就是在经历上、技术上也需要受训练。如何向人开口，如何讲说福音，什么时机带人祷告，都是有讲究的。我们向人传福音的时候，不要问他信不信，要不要得救？总要在灵里引导他要信，要悔改，要得救；并且带他用灵呼求、祷告。也不要问他要不要受浸？你就去帮助他受浸。有的人不懂这个，和人谈福音，越谈人越不信。你若是和人谈福音，半个钟头之内不能叫他信主，就不要谈了，留到下一次再来叩访。关于这些技术上的事，我们也需要有一点操练。\n再者，喂养初信者也需要训练；要像母亲顾惜自己的孩子一样。不是要求人，乃是供应人。我们去看望人的时候，不是板起面孔，而是亲切、欢欣，面带笑容。我们这个人必须是释放的，灵是敞开的，心是快乐的，口是赞美的。若是你还忧虑，还有痛苦，或还有罪担，你这样去喂养人，一定不成功，因为你还没有得释放，你仍受撒但的捆绑。因此，我们去看望人、喂养人的时候，要先祷告，要祷告到透了、通了。我们是一个得释放的人，没有重担，没有捆绑，没有忧愁，完全是喜乐的、饱满的。我们全人若是释放的，我们去看望人，人也就释放了、喜乐了。我稍微形容一点，给大家看见我们去喂养初信者，需要在各方面受训练。\n然后，我们还要去教导、成全圣徒，这要花更大的工夫。生是一回事，养是一回事，教又是另一回事；生不容易，养更难，教更麻烦。所以我们要受训练，这样我们才能成功。上一篇信息我们说过，我们参加小排聚会，第一件事要学习敞开。我们是一个敞开的人，心敞开，两手敞开，两眼敞开，口也敞开，连鼻孔也敞开；我们必须这样敞开才可以。假使我来到小排聚会，我的口闭住，我的鼻子塌下去，眼睛也闭起来，我全人都是关闭的，就是坐在那里。别人祷告，我没有声音；别人说话，我也不睬。我来聚小排聚会，只会把大家连累了。若大部分的人如此，这个小排就不能聚了。所以，还没有来聚会以前，我们从家里，在路上就开始祷告、赞美了。到了聚会中，我们整个人就是敞开的。\n还有，我们的交通也需要学习。有时候，我们不开口，一个字也不讲；一开口，就讲故事，说个没完，这就不行了。在代祷的事上，我们也需要训练。祷告的话最好要短、中肯、不啰嗦。主在教导门徒的祷告中，每一句都是真实、中肯，不长也不啰嗦（太六9~13）。有信心的祷告，话语是简单地，一说就中的。在小排聚会里，也要学习发问，问在点上。发问之后，无论是真理上的或生命上的，人人都可以试着回答，就着自己所知道的，彼此说出来。弟兄姊妹中间，多少都有一些属灵的积蓄。我们爱主多年，经历主也很多，我们都有一些积存的丰富。每当有人提出问题，每一个都把自己所知道的说出来。你说，我说，大家说。这样，不仅答复了那发问的人，同时也叫一切与会的人都得着帮助；结果，就叫大家受了教导，同时也享受基督身体的丰富。所以，在小排聚会里大家发言，大家教导，大家学习，乃是学习真理并生命长进最上的一条路。一年五十二周，我们每周最少有一次这样的小排聚会，一年过一年我们在真理和生命上将要受到何等的成全。弟兄姊妹所积存属灵的丰富就能一代一代传下去，这丰富就存在召会中，且是无可限量的。这绝不是任何的个人能代替的。然而，这在我们中间需要有一个开头，立下一个基础，还需要有许多的训练。\n\n圣经中申言的意义\n\n现在，我们来到新约福音祭司工作最高的一点，就是申言建造召会。照圣经所说，这一点是太高，也太重要了。二千年来，主的召会在地上几乎把这一点失掉了。申言，照原文的意思，就是替神说话，把神的话申述出来。所以圣经称为神说话的人为申言者。这和一般所说的先知意义不同。先知是重在一个人有先见之明，能说预言。但圣经这辞原来的意思并不是这样，乃是指一个为神说话，且说出神来的人。当然，申言者所说出来的话有一些是关乎预言的，但大多数都不是关乎预言的，乃是把神的话说给神的百姓听。如旧约以赛亚书有六十六章，其中预言的成分虽有却不多，大部分都是为神说出神的百姓所需要的话。我们这些新约福音的祭司在罪人身上作工，先把他们救来归神，使他们重生；接着喂养照顾他们，使他们在生命上长大，然后借着教导成全他们，使他们也能传福音，还能喂养、教导别人。到这个地步，他们在生命上有了经历，在真理上也有了深造，并且是一个常常和主交通的人，常常从主得着启示。很自然的，当环境需要的时候，他们就能为主说话，这就是申言。\n\n申言建造召会是福音祭司尽职的完成\n\n在新约中，有一章圣经专特说到申言这件事，那就是哥林多前书十四章。这一章圣经共四十节，一开头就说，“你们要追求爱，更要切慕属灵的恩赐，尤其要切慕申言。”（1）这是因为申言乃是超越的恩赐。十二节说，“你们…既渴慕灵，就要为着召会的建造，寻求得以超越。”超越一辞，原文指充盈、满溢、洋溢，也指超越。照本节上下文看，这字在此不是指满溢增多，乃是指超越不凡。使徒保罗在这里指明说方言不如申言，说方言是造就自己，申言是建造召会（4~5）。我们追求主到一个地步，就是要能申言，为主说话，并说出主，把主说到人里面，供应基督以建造召会。因此，申言是超越的，是一个人追求属灵的高峰。\n我们要达到这样一个超越的恩赐并不容易，但保罗说，“你们都能一个一个地申言，为要使众人有学习，使众人得勉励。”（31）他在三节也说，“那申言的，是对人讲说建造、勉励和安慰。”二十四节他又说，申言能把人的情形审明，把人劝服了。这些都描述出我们申言乃是说出神，并神对人的心意，叫人得造就，叫召会得建造，也就是建造基督生机的身体。可见申言是最超越的，虽比较难，却是我们都能达到的。二千年来，由于这件事比较难作，召会就没有去理会这件事，以致今天在基督教中我们看不见林前十四章所说聚会的光景。\n\n申言建造召会是福音祭司尽职的目标\n\n林前十四章给我们看见什么是召会正当地聚会。当全召会聚在一起的时候，每一个人都可以有得说的；有人说诗歌，有人说教训，有人说启示，所以是彼此说，大家说。照着我们的实行，这样作是不太容易，但不是不能作到。基督教一人讲众人听的聚会容易作，但并不符合神的心意。为使信徒人人都能申言，我们可以把聚会分成好几个地方，约五十人左右，使弟兄姊妹都有均等的机会来为主说话，并且个个都能受一点的训练。我再说，圣经给我们看见的路乃是我们个个都去传福音，叫人得重生，被点活，并喂养、教导、成全人，在真理上有认识，在生命上有经历，使他逐渐的能作见证，并为主申言，将基督供应人，使召会得着生机的建造。\n这样着来，申言建造召会乃是新约福音祭司尽职的完成，也是新约福音祭司尽职的目标。只要我们愿意操练，我信我们大家都能作到。每次聚会，我们就是操练讲，个个讲，越讲就越会讲了。你们中间有丰富的道，甚至每一个人里面也都有，但过去都给埋没了。这一次我来，就是要把你们都挖出来。我愿意你们竭力追求，达到此一目标。我实在推崇这件事，像保罗在林前十四章所推崇的一样。所以我也鼓励你们大家切慕申言，并且你们个个都能申言。借此，每个肢体的功用都能发挥出来，基督身体的丰富也都能从众肢体里面释放出来。到一个地步，基督的身体就要被建造起来，而完成神新约的经纶。\n李常受弟兄于主后一九八九年四月三十日讲于韩国汉城\n\n第四篇"
    },
    {
      "number": 5,
      "title": "第五篇 新约福音祭司尽职的条件",
      "content": "读经：箴四18，林后四16，加五25，罗八4，腓二14，加五26，林前一10，弗四14，提前一3~4，太二六41，罗十二11，西一29，林前十五58，腓三20，林后五10。\n\n纲目\n\n壹晨晨复兴─箴四18贰日日得胜─林后四16叁时时活在灵中─加五25肆事事照着灵而行─罗八4一无怨言、无争论─腓二14二无己意、无贪图─加五26伍与圣徒同心合意，彼此和谐─林前一10陆不受教训之风吹动─弗四14柒不传与神新约福音祭司体系不同的教训─提前一3~4捌儆醒祷告、殷勤劳苦，竭力奋斗，完成神新约福音祭司职责的每步工作─太二六41，罗十二11，西一29，林前十五58玖等候主来，在祂审判台前的亮光之下生活工作─腓三20，林后五10\n在已过的信息中，我们看见神新约福音的祭司个个都应该作这四件大事：第一，前去传福音救罪人；第二，喂养照顾初信的人；第三，教导成全圣徒；第四，申言建造召会。我深深地知道这些事，特别是末了二项，牵连实行的方面很多；到底小排聚会里，该怎样发问，怎样解答，怎样学习，怎样教导，尤其是在聚会中的申言，这更是一件新事，究竟我们如何能把一人讲众人听改成彼此讲互相听；我相信这些都是你们很想知道的。\n\n少数的恩赐成全所有的圣徒\n\n以弗所四章说到成全圣徒，林前十四章说到圣徒个个申言。作使徒的，作申言者的，作传福音者的，或作牧人和教师的，他们不是仅仅去作这些工，乃是要成全圣徒也能作他们所作的。传福音者不是就自己去传福音，乃是成全别人和他一样能传福音。若是光靠几个有传福音恩赐的人去传福音，那能传福音的人就太少了。结果就使少数人成为圣品阶级的传福音者，其他大多数人都成了平信徒。这样的分别是最不合乎圣经的。新约是要我们每一个得救的信徒都是“圣品阶级”，不许可有谁作平信徒。我们所有得救的人都是蒙神呼召、有圣品阶级的人。\n至于申言，更是如此。我们有个错误的观念，以为替神说话，把神说出去，这件事太大了，不是个个圣徒都能作得来的。但新约却是告诉我们说，我们每一个信徒都能申言，并没有分别。若是只有一班圣品阶级的人作申言者，其他的人都是平信徒，就会形成一种宗教组织。在天主教，就有很强的宗教阶级制度。他们甚至说圣经只有圣品阶级的人在教皇的带领下才能明白，平信徒非但不能替神说话，连明白神的话都没有资格。这是极大的错误。至于更正教，虽然主后一千五百多年时，圣经就从天主教的捆锁中释放了出来，陆续翻成多国的语言；到了今天，几乎无论在全球那个地方，都可以取得这本圣经，但许多人来读的时候，仍然是不得其门而入。\n圣经是一本神所启示的神圣之书，其中有很多特殊的名词，不是一般人所能理解的。所以在神的儿女中，神兴起一班作教师的人，把圣经中神的圣言解释、陈明给人。我们记得在徒八章说到有个埃提阿伯的太监，坐在车上念以赛亚书，却不知道所说的是什么。这时，腓利受那灵的差遣，到他的车前问他说，“你所念的，你明白么？”他说，“没有人指引我，怎能明白？”腓利就开口，从这经上起，向他传耶稣为福音（26~35）。在路加二十四章，主复活之后，向门徒们显现，开他们的心窍，使他们能明白圣经（44~45）。主耶稣和腓利所作的，就是今天作教师的所要作的。他们专一的职分就是把神所启示的圣经解释给神的儿女，把圣言教导每一个圣徒。结果，便叫每一位圣徒都能教导人圣经。\n\n成全圣徒都会作新约职事的工作\n\n以弗所四章给我们看见，升天的元首基督在升天里将恩赐赐给召会，就是祂的身体，好为着成全圣徒。成全，在原文有装备，用功用供应的意思。这些有恩赐的人装备、教导、供应每一个圣徒，使他们个个都能作有恩赐的人所能作的。作使徒的就成全圣徒也能作使徒，到各地传福音，设立召会。但今天在基督徒中间，我们看不见这种光景，我们只看见作使徒的、申言的、传福音的，出去到处作他们所能作的工，别人一概不会。这种光景是反常的，是把以弗所四章摆在一边的。所以认真说，这一章圣经已有十九个世纪被基督徒忽略了。一提到设立召会，大家一般的观念都认为这是使徒们作的，一般人是作不来的。但圣经以弗所四章是说使徒成全圣徒，好叫他们能作使徒所作的。\n使徒们所作的乃是新约的职事。新约的职事主要的，第一，就是传福音。主复活后，亲自向那些跟随祂的门徒显现，嘱咐他们要去，使万民作主的门徒，将他们浸入父、子、圣灵的名里（太二八19），好与三一神有生机的联结。当初的门徒们能作这事，是因为主亲自带他们三年半，教他们作这事。到了行传我们就看见，使徒们在耶路撒冷传耶稣是基督为福音，带领许许多多的人归主。不但如此，他们也教导众圣徒会传福音。因此，在徒八章，当耶路撒冷的召会大遭逼迫时，门徒都分散到各地，就把福音传出去了。\n第二，就是喂养主的小羊。在约翰二十一章，主要祂的门徒彼得喂养祂的小羊。以后，彼得就在圣徒中间喂养主的小羊，就是幼弱的信徒，并且他也教导、劝勉人要喂养、照管主的羊（彼前五1~4）。第三，就是照以弗所四章成全、装备、供应每一个信徒。第四，就是要使圣徒达到一个境地，个个都能申言，为主说话。传福音，喂养小羊，成全圣徒，以及为主申言，这四步加起来，就是建造基督的身体；不是建造一个组织的会，乃是建造一个生机体。\n假定有八个家，八对夫妇搬到一个没有召会的城。他们该怎样设立召会？他们乃是新约福音的祭司，头一步的工作就是传福音救罪人。他们十六位可以分队出去到人那里，不是请人来听福音，乃是去传福音给人，作得人的渔夫。我敢担保，这样去传福音，一定会得人。然后，就喂养、照顾这些新得救的人，并且一步步成全他们，使他们也会作福音祭司的工作。如此召会就成立了。进一步，他们还要被建造在一起，成为基督生机的身体。所以，在你们出去之先，需要被成全；需要有使徒、申言者、传福音者、牧人和教师来成全你们，使你们都能作职事的工作。\n\n操练申言\n\n主在我们中间也要恢复林前十四章的申言，为主说话以建造召会。一人讲众人听的聚会，不是一点益处都没有，但它的害处却是叫那些一直听道的人，到一个地步只会听而不会说了。你们知道，我们身体上的肢体都需要操练。假使我这两条腿不走路，就是躺在床上，经过一年的工夫，等到要下床时，不要说不能走了，恐怕连站也不能站了。同样，我们每一个得救的人，都是基督身体上的肢体，都有生机的功能，都能传福音、喂养小羊、成全圣徒、并且申言。但是，因着长久以来光听而不说，以致我们那能为主作出口的生机功能，不但没有得着启发，反倒被抹煞了。所以从现在起，我们的聚会不仅是为着听，也要操练说；有听，有说，慢慢不说的也说了。结果，个个都能说，到那时候，每一个人都能申言了。\n\n为主申言的路\n\n我可以告诉大家，申言是由三件东西构成的，第一，有圣经的知识，对圣经熟悉；第二，在主里有经历，不仅真理深入，生命也有经历；第三，亲近主，与主交通、联结。我们亲近主，最好是在早晨，借着读主的话与主交通。每天早晨，不必读太多，最多读七、八节经言就可以了；然后从这些经言中找出两节最有意义的，一面祷，一面读。这样，花十五或二十分钟，一定会有灵感，再把这灵感写下来。一周七个早晨，每早晨都这样享受主，从祂的话中得着灵感。到了主日，把已过七天所得的灵感加在一起，就成了一篇申言；在聚会时，就可以照着这一篇申言了。这是一条路，尤其是刚开始操练时，每个人都很容易作得到。只要我们天天读主的话，与主有交通，我们就会从主得着亮光。结果，我们把圣经的知识、生命的经历、以及属灵的亮光加在一起，就可以为主申言了。\n我盼望长老、同工们能这样率先操练，然后再训练众弟兄姊妹也这样操练。最好是弟兄姊妹能写一篇申言稿，给施训的人看一看，改一改，到了主日申言一过，再批一批。虽然申言时有稿子，但不是呆板的照着读，乃是自然的说这一篇话。说的时候，若是有临时的感觉，也可以加上一、二句，就更活泼、更有亮光了。若是我们肯这样受训练，我信操练一个月下来，我们都能申言了。到那时候，你们就可以把一人讲众人听改作个个讲互相听了。为使聚会能丰富，有享受，众人能说出一个东西来，有的时候彼此说互相听不一定有把握，所以负责的弟兄还得作准备。若是弟兄姊妹能申言出丰富来，与会的人都满意，吃了一个饱，那就可以了；否则，还需要在末了，根据弟兄姊妹所说的，讲出八至十分钟的话语，刚刚强强、丰丰富富、活活泼泼的释放一篇信息，好叫大家得供应，得饱足。这样的准备是为着作补救，好维持、加强召会申言的聚会。\n这样作个一、二年，你们这里召会的申言就会丰富，就有了基础。并且，大家天天都在那里得复兴，都深入主的话，都对主有丰富的享受，全召会就复兴了，个个都成了新约福音的祭司，都作使徒、申言者、传福音者、牧人和教师的工作，没有一个是闲懒而不结果子的；个个都是圣品阶级，没有一个是平信徒。如果我们有三千信徒都是这样，个个都能生，也能养，还能教，就算一年带进一人，一年就翻一倍，三千变六千了。年年这样下去，那真是召会大大兴旺了。每一个信徒都是福音的祭司，人人传福音，人人喂养主的小羊，人人成全圣徒，人人为主申言，召会也就建造起来了。\n\n福音祭司尽职的条件\n\n为着这荣耀的目标与结果，我要说到新约福音祭司尽职的条件。这些条件说出我们是怎样的一个人，过的是怎样的生活。你若是一个不爱主，爱世界，还活在罪中的人，你就不够条件作新约福音的祭司。这里，我共列了九大项，说到一个作新约福音祭司的人，并他所过的生活。第一，晨晨复兴。每天早晨，我们都要到主面前得着复兴，使我们的生活像黎明的光，越照越明（箴四18）。第二，日日得胜。哥林多后书四章所说的更新就是得胜。我们留在老旧里，就是失败；我们天天更新就是日日得胜。第三，时时活在灵中。不凭着肉体，魂生命，老旧的己，乃凭着灵活着（加五25）。第四，事事照着灵而行。不照着自己的意见、理由，乃照着灵而行（罗八4）；灵怎样引导，就怎样作。一个照着灵而行的人，没有怨言，没有争论（腓二14）；也没有己意，更没有贪图（加五26）。第五，与圣徒同心合意，彼此和谐（林前一10）；在主里有一样的心思，说一样的话。\n第六，不受教训之风吹动（弗四14）。基督徒中间，一注意道理，就有意见，就会产生分裂。但我们只要基督并祂的身体，并为此而活。第七，不传与神新约福音祭司体系不同的教训（提前一3~4）。我们已清楚看见新约神所命定的路，就是人人作福音的祭司，为神尽职；我们不讲也不接受和这真理不同的任何教训。第八，儆醒祷告、殷勤劳苦，竭力奋斗，完成神新约福音祭司职责的每步工作（太二六41，罗十二11，西一29，林前十五58）。第九，作一个等候主来的人，在祂审判台前的亮光之下生活工作（腓三20，林后五10）。这九大点乃是全本新约的一个摘要。全本新约就是要我们作这样的人，过这样的生活。结果，我们就够条件作新约福音的祭司。\n祷告：主啊，我们实在赞美你，在这几天，你把命定的路指给我们看，把圣经的启示向我们打开。感谢你，这几天在这里天是敞开的，也是明亮的，有四干多圣徒接受你的话。但愿他们的路都是义人的路，如同黎明的光，越照越明，直到日午。更愿他们都是爱你的人，如日头出现，光辉烈烈。主啊，为着你在这里的召会，你祝福大韩民国，祝福这民族，也祝福这地。更祝福凡称为你名下的人，都能作一个活的信徒，成为新约福音的祭司，个个传福音，个个喂养主的小羊，个个成全圣徒，个个申言，以建造基督生机的身体。但愿你的经纶完成，你的计划成就。你得着荣耀，魔鬼受羞辱，众圣徒都得祝福。荣耀归与你的名。阿们。\n李常受弟兄于主后一九八九年四月三十日讲于韩国汉城\n\n第五篇"
    }
  ]
}