{
  "id": "xlcl-043",
  "title": "09 设立排聚会",
  "format": "html",
  "chapters": [
    {
      "number": 1,
      "title": "设立排聚会",
      "content": "## 学习一再的尝试\n我们必须竭力开始有排聚会。然而，要建立排聚会并不容易。你头一次尝试可能不成功。你必须一试再试。你必须召集所有在你照顾下的新人，如果你没有那么多人，你可以与别的队一同作工。可能需要把三队所有的新人召集在一起，成为一个排聚会。\n## 作排聚会的教练\n你们一旦来在一起，就必须帮助新人，带领他们正确的实行排聚会。你必须是他们的‘教练’，因为他们都是新的学习者。你可以借着向他们题议或发问而帮助他们。你可以问：‘弟兄们，过去几天你们有什么难处？’这会帮助他们学习如何交通，如何彼此敞开。\n1、引导进入排聚会各点\n作为基督徒，我们“不再是外人和寄居的，乃是…神家里的亲人”。(弗二19。)我们是在基督里的弟兄姊妹，所以我们喜欢向家中别的肢体敞开自己。我们敞开自己让别人知道我们的光景，这是很好的。有一位弟兄可能向你敞开，让你知道他的难处，这时你怎么办？你最好不要带头为他祷告。你可以问别人：‘我们该作什么？’别人会说，‘对，我们该为他祷告，我们也该为彼此祷告。在祷告之后，我们或者可以说一些话，把他们引到彼此相顾的事上。不论人的情形如何，爱总会摸着人，总会建造人。\n2、带领有感觉的一同牧养\n彼此相顾能带你进到实际的牧养里。你可以说，‘某某弟兄，或许你明天可以和我一同去帮助这位弟兄。’这就是牧养。这样，你就能在排聚会里带领。然而，你不可有任何感觉或意识，自以为是带领的。你一有了这种意识，就成了领头人，这会杀死聚会。\n3、给新人看见榜样跟从\n你若给新人看见这路，他们会学习跟从你的榜样。他们若不知道如何发问，你可以作给他们看。你可以问：‘你们都知道人有灵么？你们都知道什么是人的灵么？’你这样发问，并让他们回答。他们的回答就是一种彼此的教导。然后你可能需要加一些话，但不要回答得太快。你若说得太早，可能会使新人不说话。你必须鼓励他们说话，并给他们机会说话。在他们回答后，你可以加一些话，然后另一人可以加一些话，等等。最后，你们会得着一个完整的答案，这答案就成了非常好的教训。借此所有的新人会认识、看见、并明白他们有人的灵。此外，借着这样的发问和回答，你就给他们设立榜样，让他们跟从。\n## 学习照着新排聚会的步骤\n从老旧的实行改到新的实行是不容易的。我们可以从少数人开始排聚会，甚至四、五人就够了。最好主要的是与新人开始排聚会。我们设立那个排聚会后，可以带进更多圣徒。我们必须照着这几个步骤有排聚会：第一，我们必须让与会者敞开，使大家能有交通。交通后我们会知道圣徒们的光景和情形，使我们可以为彼此祷告。这是代祷。然后，根据我们的交通和祷告，我们可以彼此有一些实际的相顾，有一些实际相互的牧养。在每一次排聚会，我们必须有一些重点可以谈论，或题出问题给人回答。这是彼此教导，不是一人作，乃是全体与会者共同作。人人都可以说一点话，甚至这一点话也应当看作教导的一部分。我们必须尽力这样实行排聚会。\n## 晨晨复兴，日日得胜的生活\n在新路中实行召会生活很重要的一件事，乃是过晨晨复兴，日日得胜的生活。我们不该认为很难有个人的晨兴。得复兴就是重新被主摸着。每逢主摸着我们，我们就得着复兴。我们强调晨晨复兴，这是基于神自然的律。《神命定之路的操练与实行》第二十八篇\n## 设立排聚会(问答)\n1、如何开始有排聚会？\n2、如何作排聚会的教练？"
    }
  ]
}